matplotlib_qml/__init__.py
matplotlib_qml/artist.py
matplotlib_qml/axis.py
matplotlib_qml/cm.py
matplotlib_qml/collections.py
matplotlib_qml/colorbar.py
matplotlib_qml/event.py
matplotlib_qml/factory.py
matplotlib_qml/graphs_2d.py
matplotlib_qml/image.py
matplotlib_qml/init_matplotlib_bridge.py
matplotlib_qml/patches.py
matplotlib_qml/plot_objects.py
matplotlib_qml/plugin_loader.py
matplotlib_qml/utils.py
matplotlib_qml/plugins/__init__.py
matplotlib_qml/plugins/annotation.py
matplotlib_qml/plugins/bar.py
matplotlib_qml/plugins/dummy_axis.py
matplotlib_qml/plugins/fill_between.py
matplotlib_qml/plugins/imshow.py
matplotlib_qml/plugins/lines.py
matplotlib_qml/plugins/scatter.py
matplotlib_qml/plugins/span.py
matplotlib_qml_bindings-1.0.2.dist-info/licenses/COPYING
matplotlib_qml_bindings-1.0.2.dist-info/licenses/COPYING.LESSER
matplotlib_qml_bindings-1.0.2.dist-info/METADATA
matplotlib_qml_bindings-1.0.2.dist-info/WHEEL
matplotlib_qml_bindings-1.0.2.dist-info/top_level.txt
matplotlib_qml_bindings-1.0.2.dist-info/RECORD
