Metadata-Version: 2.4
Name: matplotlib-qml-bindings
Version: 1.0.2
Summary: Bindings to use matplotlib components in a QML-like syntax inside of QML-components
Author-email: Nicklas Osmers <nosmers@qass.net>
Project-URL: Homepage, https://github.com/QASS/matplotlib-qml
Classifier: Programming Language :: Python :: 3
Classifier: License :: OSI Approved :: GNU Lesser General Public License v3 (LGPLv3)
Classifier: Operating System :: OS Independent
Requires-Python: >=3.6
License-File: COPYING
License-File: COPYING.LESSER
Requires-Dist: numpy>=1.19.5
Requires-Dist: matplotlib>=3.3.3
Requires-Dist: matplotlib<3.7
Requires-Dist: matplotlib_backend_pyside2==0.0.11
Provides-Extra: pyside2
Requires-Dist: matplotlib_backend_pyside2[pyside2]; extra == "pyside2"
Dynamic: license-file
